setup.py
queuetools/__init__.py
queuetools/bindq.py
queuetools/hammer.py
queuetools/mkq.py
queuetools/mkx.py
queuetools/options.py
queuetools/qcat.py
queuetools/qpurge.py
queuetools/rmq.py
queuetools/rmx.py
queuetools/unbindq.py
queuetools.egg-info/PKG-INFO
queuetools.egg-info/SOURCES.txt
queuetools.egg-info/dependency_links.txt
queuetools.egg-info/entry_points.txt
queuetools.egg-info/requires.txt
queuetools.egg-info/top_level.txt