Metadata-Version: 1.0
Name: queuetools
Version: 1.2
Summary: A set of scripts for configuring AMQP brokers.
Home-page: http://alchemy.grimoire.ca/hg/queuetools/
Author: Owen Jacobson
Author-email: owen.jacobson@grimoire.ca
License: UNKNOWN
Download-URL: http://alchemy.grimoire.ca/python/releases/queuetools/
Platform: UNKNOWN
Classifier: Development Status :: 5 - Production/Stable
Classifier: Environment :: Console
Classifier: Intended Audience :: Developers
Classifier: Intended Audience :: System Administrators
Classifier: License :: OSI Approved :: MIT License
Classifier: Operating System :: OS Independent
Classifier: Topic :: Software Development
Classifier: Topic :: System :: Systems Administration
Classifier: Topic :: Utilities
